Feature_Engineering_Pipeline
