Metadata-Version: 1.0
Name: fraud-package
Version: 0.5
Summary: Fraud detection Feature Engineering Pipeline
Home-page: UNKNOWN
Author: UNKNOWN
Author-email: UNKNOWN
License: UNKNOWN
Platform: UNKNOWN
